pykit/__init__.py
pykit/config.py
pykit/stopwatch.py
pykit/utdocker.py
pykit/ututil.py
pykit/argchecker/__init__.py
pykit/argchecker/checker.py
pykit/argchecker/test/__init__.py
pykit/argchecker/test/test_checker.py
pykit/aws/__init__.py
pykit/aws/error_code.py
pykit/awssign/__init__.py
pykit/awssign/awssign.py
pykit/awssign/test/__init__.py
pykit/awssign/test/test_add_auth.py
pykit/awssign/test/test_add_post_auth.py
pykit/awssign/test/test_signer.py
pykit/cacheable/__init__.py
pykit/cacheable/cacheable.py
pykit/cacheable/test/__init__.py
pykit/cacheable/test/test_cacheable.py
pykit/cachepool/__init__.py
pykit/cachepool/cachepool.py
pykit/cachepool/test/__init__.py
pykit/cachepool/test/test_cachepool.py
pykit/cgrouparch/__init__.py
pykit/cgrouparch/account.py
pykit/cgrouparch/blkio.py
pykit/cgrouparch/cgroup_manager.py
pykit/cgrouparch/cgroup_util.py
pykit/cgrouparch/communicate.py
pykit/cgrouparch/cpu.py
pykit/cgrouparch/manager.py
pykit/cgrouparch/model.py
pykit/cgrouparch/util.py
pykit/cgrouparch/test/__init__.py
pykit/cgrouparch/test/test_blkio.py
pykit/cgrouparch/test/test_cpu.py
pykit/csvutil/__init__.py
pykit/csvutil/csvutil.py
pykit/csvutil/test/__init__.py
pykit/csvutil/test/test_csvutil.py
pykit/daemonize/__init__.py
pykit/daemonize/daemonize.py
pykit/daemonize/test/__init__.py
pykit/daemonize/test/bar.py
pykit/daemonize/test/close_fds.py
pykit/daemonize/test/foo.py
pykit/daemonize/test/test_daemonize.py
pykit/dictutil/__init__.py
pykit/dictutil/dictutil.py
pykit/dictutil/fixed_keys_dict.py
pykit/dictutil/test/__init__.py
pykit/dictutil/test/test_dictutil.py
pykit/ectypes/__init__.py
pykit/ectypes/block_desc.py
pykit/ectypes/block_group.py
pykit/ectypes/block_group_id.py
pykit/ectypes/block_id.py
pykit/ectypes/block_index.py
pykit/ectypes/idbase.py
pykit/ectypes/region.py
pykit/ectypes/replication_config.py
pykit/ectypes/server.py
pykit/ectypes/test/__init__.py
pykit_bsc_s2-1.0.1.dist-info/METADATA
pykit_bsc_s2-1.0.1.dist-info/RECORD
pykit_bsc_s2-1.0.1.dist-info/WHEEL
pykit_bsc_s2-1.0.1.dist-info/top_level.txt
