Metadata-Version: 2.1
Name: pykit-bsc-s2
Version: 1.0.1
Summary: A collection of toolkit lib for distributed system development in python
Home-page: https://github.com/bsc-s2/pykit
Author: Zhang Yanpo
Author-email: drdr.xp@gmail.com
License: MIT
Platform: UNKNOWN
Classifier: Programming Language :: Python :: 2.7
Classifier: License :: OSI Approved :: MIT License
Classifier: Operating System :: OS Independent
Requires-Python: >=2.7,!=3.0.*,!=3.1.*
Requires-Dist: PyYAML (==3.11)
